multicloud_storage/__init__.py
multicloud_storage/clients/__init__.py
multicloud_storage/clients/minio_client.py
multicloud_storage/clients/oss_client_v2.py
multicloud_storage/clients/s3_compat_client.py
multicloud_storage/core/__init__.py
multicloud_storage/core/base.py
multicloud_storage/core/exceptions.py
multicloud_storage/core/factory.py
multicloud_storage/core/providers.py
multicloud_storage/core/registry.py
multicloud_storage/core/result.py
multicloud_storage/core/url_parser.py
multicloud_storage/core/utils.py
multicloud_storage-0.1.7.dist-info/METADATA
multicloud_storage-0.1.7.dist-info/WHEEL
multicloud_storage-0.1.7.dist-info/entry_points.txt
multicloud_storage-0.1.7.dist-info/top_level.txt
multicloud_storage-0.1.7.dist-info/RECORD
